[
  {
    "timestamp": "2025-12-17T16:25:29.557733",
    "activity_type": "code",
    "description": "Update dependencies fixing edge cases",
    "energy_level": 70,
    "focus_score": 81
  },
  {
    "timestamp": "2025-12-17T20:21:08.326452",
    "activity_type": "planning",
    "description": "Improve targeting for production readiness",
    "energy_level": 91,
    "focus_score": 84
  },
  {
    "timestamp": "2025-12-18T08:26:17.375887",
    "activity_type": "documentation",
    "description": "Improve mobile responsiveness for better user experience",
    "energy_level": 68,
    "focus_score": 96
  },
  {
    "timestamp": "2025-12-18T12:38:27.870285",
    "activity_type": "planning",
    "description": "🚀 Deploy new version based on user feedback",
    "energy_level": 85,
    "focus_score": 87
  },
  {
    "timestamp": "2025-12-18T16:26:38.997763",
    "activity_type": "documentation",
    "description": "⚡ Performance optimization following best practices",
    "energy_level": 81,
    "focus_score": 71
  },
  {
    "timestamp": "2025-12-18T20:18:34.459196",
    "activity_type": "planning",
    "description": "Add analytics with latest standards",
    "energy_level": 79,
    "focus_score": 75
  },
  {
    "timestamp": "2025-12-19T08:26:07.855532",
    "activity_type": "planning",
    "description": "Add tests following best practices",
    "energy_level": 98,
    "focus_score": 72
  },
  {
    "timestamp": "2025-12-19T12:37:11.538498",
    "activity_type": "review",
    "description": "Add new feature idea optimizing workflow",
    "energy_level": 63,
    "focus_score": 77
  },
  {
    "timestamp": "2025-12-19T16:23:01.047079",
    "activity_type": "review",
    "description": "Update dependencies to improve maintainability",
    "energy_level": 95,
    "focus_score": 70
  },
  {
    "timestamp": "2025-12-19T20:19:54.341355",
    "activity_type": "planning",
    "description": "Add internationalization for better user experience",
    "energy_level": 73,
    "focus_score": 100
  },
  {
    "timestamp": "2025-12-20T08:22:54.880757",
    "activity_type": "review",
    "description": "Update documentation to improve maintainability",
    "energy_level": 71,
    "focus_score": 83
  },
  {
    "timestamp": "2025-12-20T12:34:20.921645",
    "activity_type": "planning",
    "description": "Fix minor bug to improve maintainability",
    "energy_level": 66,
    "focus_score": 84
  },
  {
    "timestamp": "2025-12-20T16:20:47.304790",
    "activity_type": "review",
    "description": "Update documentation based on user feedback",
    "energy_level": 74,
    "focus_score": 77
  },
  {
    "timestamp": "2025-12-20T20:18:16.507442",
    "activity_type": "review",
    "description": "🚀 Deploy new version for better user experience",
    "energy_level": 83,
    "focus_score": 83
  },
  {
    "timestamp": "2025-12-21T08:22:50.830396",
    "activity_type": "documentation",
    "description": "🔒 Security update based on user feedback",
    "energy_level": 92,
    "focus_score": 88
  },
  {
    "timestamp": "2025-12-21T12:34:42.366312",
    "activity_type": "planning",
    "description": "Update dependencies following best practices",
    "energy_level": 63,
    "focus_score": 74
  },
  {
    "timestamp": "2025-12-21T16:20:24.960260",
    "activity_type": "documentation",
    "description": "Improve code structure optimizing workflow",
    "energy_level": 95,
    "focus_score": 72
  },
  {
    "timestamp": "2025-12-21T20:19:10.011771",
    "activity_type": "documentation",
    "description": "🚀 Deploy new version fixing edge cases",
    "energy_level": 96,
    "focus_score": 87
  },
  {
    "timestamp": "2025-12-22T08:27:25.705199",
    "activity_type": "review",
    "description": "Add analytics improving code quality",
    "energy_level": 60,
    "focus_score": 76
  },
  {
    "timestamp": "2025-12-22T12:38:13.666364",
    "activity_type": "documentation",
    "description": "Fix CI build for production readiness",
    "energy_level": 68,
    "focus_score": 91
  },
  {
    "timestamp": "2025-12-22T16:22:59.960782",
    "activity_type": "code",
    "description": "🔒 Security update to improve maintainability",
    "energy_level": 100,
    "focus_score": 95
  },
  {
    "timestamp": "2025-12-22T20:20:30.208785",
    "activity_type": "planning",
    "description": "Add internationalization optimizing workflow",
    "energy_level": 90,
    "focus_score": 94
  },
  {
    "timestamp": "2025-12-23T08:26:45.093480",
    "activity_type": "planning",
    "description": "Improve SEO for production readiness",
    "energy_level": 92,
    "focus_score": 73
  },
  {
    "timestamp": "2025-12-23T12:38:53.313853",
    "activity_type": "code",
    "description": "Improve mobile responsiveness enhancing performance",
    "energy_level": 95,
    "focus_score": 76
  },
  {
    "timestamp": "2025-12-23T16:23:56.708585",
    "activity_type": "planning",
    "description": "Update documentation to improve maintainability",
    "energy_level": 72,
    "focus_score": 85
  },
  {
    "timestamp": "2025-12-23T20:19:33.083469",
    "activity_type": "documentation",
    "description": "Improve SEO with latest standards",
    "energy_level": 87,
    "focus_score": 81
  },
  {
    "timestamp": "2025-12-24T08:26:27.701234",
    "activity_type": "code",
    "description": "Improve mobile responsiveness enhancing performance",
    "energy_level": 80,
    "focus_score": 70
  },
  {
    "timestamp": "2025-12-24T12:38:05.922230",
    "activity_type": "documentation",
    "description": "Update dependencies following best practices",
    "energy_level": 80,
    "focus_score": 95
  },
  {
    "timestamp": "2025-12-24T16:22:33.099028",
    "activity_type": "review",
    "description": "Add internationalization for better user experience",
    "energy_level": 61,
    "focus_score": 98
  },
  {
    "timestamp": "2025-12-24T20:19:35.067120",
    "activity_type": "documentation",
    "description": "♻️ Refactor code enhancing performance",
    "energy_level": 87,
    "focus_score": 100
  },
  {
    "timestamp": "2025-12-25T08:25:14.614611",
    "activity_type": "code",
    "description": "🚀 Deploy new version with latest standards",
    "energy_level": 90,
    "focus_score": 71
  },
  {
    "timestamp": "2025-12-25T12:37:19.647336",
    "activity_type": "planning",
    "description": "Improve SEO for better user experience",
    "energy_level": 100,
    "focus_score": 78
  },
  {
    "timestamp": "2025-12-25T16:22:34.531396",
    "activity_type": "code",
    "description": "🔒 Security update for production readiness",
    "energy_level": 74,
    "focus_score": 81
  },
  {
    "timestamp": "2025-12-25T20:20:11.718420",
    "activity_type": "planning",
    "description": "Update configuration improving code quality",
    "energy_level": 67,
    "focus_score": 93
  },
  {
    "timestamp": "2025-12-26T08:24:59.432935",
    "activity_type": "documentation",
    "description": "Update documentation fixing edge cases",
    "energy_level": 60,
    "focus_score": 83
  },
  {
    "timestamp": "2025-12-26T12:37:29.181612",
    "activity_type": "code",
    "description": "Improve targeting optimizing workflow",
    "energy_level": 89,
    "focus_score": 95
  },
  {
    "timestamp": "2025-12-26T16:21:08.554323",
    "activity_type": "documentation",
    "description": "Update UI components fixing edge cases",
    "energy_level": 89,
    "focus_score": 82
  },
  {
    "timestamp": "2025-12-26T20:19:03.993601",
    "activity_type": "review",
    "description": "Fix minor bug optimizing workflow",
    "energy_level": 65,
    "focus_score": 95
  },
  {
    "timestamp": "2025-12-27T08:23:54.019374",
    "activity_type": "review",
    "description": "Update build scripts improving code quality",
    "energy_level": 69,
    "focus_score": 82
  },
  {
    "timestamp": "2025-12-27T12:35:20.601528",
    "activity_type": "code",
    "description": "Add analytics improving code quality",
    "energy_level": 69,
    "focus_score": 83
  },
  {
    "timestamp": "2025-12-27T16:21:03.535324",
    "activity_type": "planning",
    "description": "Add new feature idea fixing edge cases",
    "energy_level": 99,
    "focus_score": 78
  },
  {
    "timestamp": "2025-12-27T20:19:55.602272",
    "activity_type": "planning",
    "description": "Update build scripts optimizing workflow",
    "energy_level": 73,
    "focus_score": 71
  },
  {
    "timestamp": "2025-12-28T08:23:49.722021",
    "activity_type": "code",
    "description": "Add analytics improving code quality",
    "energy_level": 92,
    "focus_score": 80
  },
  {
    "timestamp": "2025-12-28T12:35:50.990124",
    "activity_type": "review",
    "description": "Update build scripts optimizing workflow",
    "energy_level": 97,
    "focus_score": 91
  },
  {
    "timestamp": "2025-12-28T16:21:20.529181",
    "activity_type": "documentation",
    "description": "🚀 Deploy new version improving code quality",
    "energy_level": 88,
    "focus_score": 77
  },
  {
    "timestamp": "2025-12-28T20:20:03.658493",
    "activity_type": "review",
    "description": "Improve SEO following best practices",
    "energy_level": 61,
    "focus_score": 70
  },
  {
    "timestamp": "2025-12-29T08:28:17.852367",
    "activity_type": "code",
    "description": "🔒 Security update for better user experience",
    "energy_level": 74,
    "focus_score": 74
  },
  {
    "timestamp": "2025-12-29T12:40:03.099993",
    "activity_type": "review",
    "description": "Improve SEO fixing edge cases",
    "energy_level": 79,
    "focus_score": 77
  },
  {
    "timestamp": "2025-12-29T16:22:57.005336",
    "activity_type": "documentation",
    "description": "🎉 Release new version following best practices",
    "energy_level": 62,
    "focus_score": 86
  },
  {
    "timestamp": "2025-12-29T20:21:00.288953",
    "activity_type": "planning",
    "description": "Update UI components for production readiness",
    "energy_level": 70,
    "focus_score": 91
  },
  {
    "timestamp": "2025-12-30T08:26:13.646052",
    "activity_type": "planning",
    "description": "Update documentation with latest standards",
    "energy_level": 62,
    "focus_score": 90
  },
  {
    "timestamp": "2025-12-30T12:39:01.201587",
    "activity_type": "code",
    "description": "Fix minor bug to improve maintainability",
    "energy_level": 93,
    "focus_score": 86
  },
  {
    "timestamp": "2025-12-30T16:24:07.692876",
    "activity_type": "review",
    "description": "Add tests for production readiness",
    "energy_level": 93,
    "focus_score": 89
  },
  {
    "timestamp": "2025-12-30T20:20:39.151196",
    "activity_type": "code",
    "description": "🚀 Deploy new version fixing edge cases",
    "energy_level": 65,
    "focus_score": 86
  },
  {
    "timestamp": "2025-12-31T08:26:26.591150",
    "activity_type": "review",
    "description": "Improve mobile responsiveness with latest standards",
    "energy_level": 97,
    "focus_score": 90
  },
  {
    "timestamp": "2025-12-31T12:37:59.972955",
    "activity_type": "review",
    "description": "Improve mobile responsiveness based on user feedback",
    "energy_level": 89,
    "focus_score": 73
  },
  {
    "timestamp": "2025-12-31T16:22:58.085797",
    "activity_type": "review",
    "description": "Add new feature idea optimizing workflow",
    "energy_level": 77,
    "focus_score": 83
  },
  {
    "timestamp": "2025-12-31T20:19:37.723852",
    "activity_type": "code",
    "description": "Fix CI build for better user experience",
    "energy_level": 78,
    "focus_score": 80
  },
  {
    "timestamp": "2026-01-01T08:26:21.478396",
    "activity_type": "review",
    "description": "Improve mobile responsiveness enhancing performance",
    "energy_level": 64,
    "focus_score": 81
  },
  {
    "timestamp": "2026-01-01T12:37:48.287870",
    "activity_type": "documentation",
    "description": "⚡ Performance optimization enhancing performance",
    "energy_level": 73,
    "focus_score": 72
  },
  {
    "timestamp": "2026-01-01T16:23:38.535046",
    "activity_type": "code",
    "description": "🔒 Security update to improve maintainability",
    "energy_level": 66,
    "focus_score": 82
  },
  {
    "timestamp": "2026-01-01T20:20:49.941770",
    "activity_type": "documentation",
    "description": "Add internationalization improving code quality",
    "energy_level": 74,
    "focus_score": 94
  },
  {
    "timestamp": "2026-01-02T08:26:40.238441",
    "activity_type": "review",
    "description": "🔒 Security update for better user experience",
    "energy_level": 84,
    "focus_score": 89
  },
  {
    "timestamp": "2026-01-02T12:37:01.937838",
    "activity_type": "review",
    "description": "Improve targeting fixing edge cases",
    "energy_level": 64,
    "focus_score": 93
  },
  {
    "timestamp": "2026-01-02T16:22:12.195320",
    "activity_type": "review",
    "description": "Improve SEO for better user experience",
    "energy_level": 87,
    "focus_score": 74
  },
  {
    "timestamp": "2026-01-02T20:19:54.321484",
    "activity_type": "planning",
    "description": "Update UI components for production readiness",
    "energy_level": 75,
    "focus_score": 100
  },
  {
    "timestamp": "2026-01-03T08:23:49.791420",
    "activity_type": "documentation",
    "description": "Fix CI build improving code quality",
    "energy_level": 89,
    "focus_score": 93
  },
  {
    "timestamp": "2026-01-03T12:35:28.902394",
    "activity_type": "planning",
    "description": "Update configuration improving code quality",
    "energy_level": 78,
    "focus_score": 89
  },
  {
    "timestamp": "2026-01-03T16:21:10.057923",
    "activity_type": "documentation",
    "description": "Improve targeting following best practices",
    "energy_level": 75,
    "focus_score": 93
  },
  {
    "timestamp": "2026-01-03T20:19:53.038148",
    "activity_type": "planning",
    "description": "Improve SEO optimizing workflow",
    "energy_level": 71,
    "focus_score": 82
  },
  {
    "timestamp": "2026-01-04T08:24:24.057715",
    "activity_type": "code",
    "description": "Improve targeting based on user feedback",
    "energy_level": 78,
    "focus_score": 94
  },
  {
    "timestamp": "2026-01-04T12:35:38.752898",
    "activity_type": "review",
    "description": "Update UI components with latest standards",
    "energy_level": 78,
    "focus_score": 76
  },
  {
    "timestamp": "2026-01-04T16:21:01.092374",
    "activity_type": "planning",
    "description": "Update build scripts improving code quality",
    "energy_level": 61,
    "focus_score": 95
  },
  {
    "timestamp": "2026-01-04T20:20:10.534565",
    "activity_type": "code",
    "description": "Update dependencies improving code quality",
    "energy_level": 79,
    "focus_score": 96
  },
  {
    "timestamp": "2026-01-05T08:29:20.984787",
    "activity_type": "planning",
    "description": "Update dependencies fixing edge cases",
    "energy_level": 75,
    "focus_score": 78
  },
  {
    "timestamp": "2026-01-05T12:41:21.391782",
    "activity_type": "code",
    "description": "⚡ Performance optimization for better user experience",
    "energy_level": 94,
    "focus_score": 70
  },
  {
    "timestamp": "2026-01-05T16:24:55.682994",
    "activity_type": "documentation",
    "description": "♻️ Refactor code for production readiness",
    "energy_level": 73,
    "focus_score": 70
  },
  {
    "timestamp": "2026-01-05T20:22:34.187628",
    "activity_type": "code",
    "description": "Add analytics optimizing workflow",
    "energy_level": 78,
    "focus_score": 75
  },
  {
    "timestamp": "2026-01-06T08:27:21.929063",
    "activity_type": "code",
    "description": "🔒 Security update enhancing performance",
    "energy_level": 70,
    "focus_score": 70
  },
  {
    "timestamp": "2026-01-06T12:39:43.079310",
    "activity_type": "documentation",
    "description": "Update dependencies following best practices",
    "energy_level": 100,
    "focus_score": 74
  },
  {
    "timestamp": "2026-01-06T16:25:20.464557",
    "activity_type": "planning",
    "description": "Add tests following best practices",
    "energy_level": 82,
    "focus_score": 100
  },
  {
    "timestamp": "2026-01-06T20:20:56.521104",
    "activity_type": "planning",
    "description": "🚀 Deploy new version improving code quality",
    "energy_level": 66,
    "focus_score": 91
  },
  {
    "timestamp": "2026-01-07T08:27:17.314600",
    "activity_type": "planning",
    "description": "Improve SEO fixing edge cases",
    "energy_level": 72,
    "focus_score": 70
  },
  {
    "timestamp": "2026-01-07T12:40:28.043394",
    "activity_type": "code",
    "description": "Update documentation following best practices",
    "energy_level": 90,
    "focus_score": 97
  },
  {
    "timestamp": "2026-01-07T16:27:19.124037",
    "activity_type": "review",
    "description": "Update UI components based on user feedback",
    "energy_level": 65,
    "focus_score": 88
  },
  {
    "timestamp": "2026-01-07T20:22:13.896646",
    "activity_type": "documentation",
    "description": "Update build scripts following best practices",
    "energy_level": 69,
    "focus_score": 86
  },
  {
    "timestamp": "2026-01-08T08:27:32.381243",
    "activity_type": "code",
    "description": "Add analytics with latest standards",
    "energy_level": 65,
    "focus_score": 90
  },
  {
    "timestamp": "2026-01-08T12:40:53.144978",
    "activity_type": "documentation",
    "description": "♻️ Refactor code to improve maintainability",
    "energy_level": 74,
    "focus_score": 81
  },
  {
    "timestamp": "2026-01-08T16:27:15.766451",
    "activity_type": "planning",
    "description": "🔒 Security update with latest standards",
    "energy_level": 99,
    "focus_score": 93
  },
  {
    "timestamp": "2026-01-08T20:22:20.662915",
    "activity_type": "planning",
    "description": "Update build scripts with latest standards",
    "energy_level": 90,
    "focus_score": 95
  },
  {
    "timestamp": "2026-01-09T08:27:41.587690",
    "activity_type": "review",
    "description": "Add new feature idea following best practices",
    "energy_level": 99,
    "focus_score": 93
  },
  {
    "timestamp": "2026-01-09T12:39:50.561311",
    "activity_type": "code",
    "description": "Add analytics to improve maintainability",
    "energy_level": 86,
    "focus_score": 73
  },
  {
    "timestamp": "2026-01-09T16:24:21.386745",
    "activity_type": "documentation",
    "description": "Add new feature idea based on user feedback",
    "energy_level": 98,
    "focus_score": 90
  },
  {
    "timestamp": "2026-01-09T20:21:47.763912",
    "activity_type": "planning",
    "description": "Improve SEO improving code quality",
    "energy_level": 60,
    "focus_score": 71
  },
  {
    "timestamp": "2026-01-10T08:23:07.776769",
    "activity_type": "review",
    "description": "🚀 Deploy new version fixing edge cases",
    "energy_level": 63,
    "focus_score": 77
  },
  {
    "timestamp": "2026-01-10T12:35:41.272121",
    "activity_type": "documentation",
    "description": "Fix CI build for production readiness",
    "energy_level": 91,
    "focus_score": 95
  },
  {
    "timestamp": "2026-01-10T16:21:45.785635",
    "activity_type": "documentation",
    "description": "Update configuration with latest standards",
    "energy_level": 89,
    "focus_score": 73
  },
  {
    "timestamp": "2026-01-10T20:19:40.368127",
    "activity_type": "review",
    "description": "Add tests to improve maintainability",
    "energy_level": 61,
    "focus_score": 98
  },
  {
    "timestamp": "2026-01-11T08:23:34.521898",
    "activity_type": "review",
    "description": "🔒 Security update based on user feedback",
    "energy_level": 81,
    "focus_score": 78
  },
  {
    "timestamp": "2026-01-11T12:36:21.911502",
    "activity_type": "code",
    "description": "Update dependencies for production readiness",
    "energy_level": 76,
    "focus_score": 75
  }
]